setup.py
sqlite3.py
micropython_sqlite3.egg-info/PKG-INFO
micropython_sqlite3.egg-info/SOURCES.txt
micropython_sqlite3.egg-info/dependency_links.txt
micropython_sqlite3.egg-info/requires.txt
micropython_sqlite3.egg-info/top_level.txt