Metadata-Version: 1.0
Name: micropython-sqlite3
Version: 0.2.2
Summary: sqlite3 module for MicroPython
Home-page: https://github.com/micropython/micropython/issues/405
Author: MicroPython Developers
Author-email: micro-python@googlegroups.com
License: MIT
Platform: UNKNOWN
